otlp_stdout_adapter/__init__.py
otlp_stdout_adapter/adapter.py
otlp_stdout_adapter-0.3.1.dist-info/licenses/LICENSE
otlp_stdout_adapter-0.3.1.dist-info/METADATA
otlp_stdout_adapter-0.3.1.dist-info/WHEEL
otlp_stdout_adapter-0.3.1.dist-info/top_level.txt
otlp_stdout_adapter-0.3.1.dist-info/RECORD
