Metadata-Version: 2.4
Name: otlp-stdout-adapter
Version: 0.3.1
Summary: A custom requests HTTPAdapter that serializes spans to stdout for OpenTelemetry OTLP exporters (DEPRECATED)
Author-email: Alessandro Bologna <alessandro.bologna@gmail.com>
License: MIT License
Project-URL: Homepage, https://github.com/dev7a/package-archive/tree/main/packages/python/adapter
Project-URL: Repository, https://github.com/dev7a/package-archive/tree/main/packages/python/adapter
Keywords: opentelemetry,otlp,stdout,lambda,aws
Classifier: Development Status :: 7 - Inactive
Classifier: Development Status :: 3 - Alpha
Classifier: Intended Audience :: Developers
Classifier: License :: OSI Approved :: MIT License
Classifier: Programming Language :: Python :: 3
Classifier: Programming Language :: Python :: 3.12
Classifier: Operating System :: OS Independent
Classifier: Topic :: Software Development :: Libraries :: Python Modules
Classifier: Topic :: System :: Logging
Classifier: Topic :: System :: Monitoring
Classifier: Typing :: Typed
Requires-Python: >=3.12
License-File: LICENSE
Requires-Dist: opentelemetry-api<2.0.0,>=1.0.0
Requires-Dist: opentelemetry-sdk<2.0.0,>=1.0.0
Requires-Dist: opentelemetry-exporter-otlp-proto-http<2.0.0,>=1.0.0
Requires-Dist: opentelemetry-semantic-conventions>=0.48b0
Requires-Dist: requests<3.0.0,>=2.31.0
Provides-Extra: dev
Requires-Dist: pytest>=7.0.0; extra == "dev"
Requires-Dist: black>=22.0.0; extra == "dev"
Requires-Dist: mypy>=1.0.0; extra == "dev"
Requires-Dist: pylint>=2.17.0; extra == "dev"
Dynamic: license-file
